LICENSE
ultiplayground/__init__.py
ultiplayground/closures/__init__.py
ultiplayground/closures/incrementer.py
ultiplayground/closures/multiplier.py
ultiplayground/closures/returner.py
ultiplayground/oop/animal.py
ultiplayground/oop/rabit.py
ultiplayground/snippets/__init__.py
ultiplayground/snippets/random_pokemon.py
ultiplayground/snippets/random_quotes.py
ultiplayground-0.1.5.dist-info/LICENSE
ultiplayground-0.1.5.dist-info/WHEEL
ultiplayground-0.1.5.dist-info/METADATA
ultiplayground-0.1.5.dist-info/RECORD
