Metadata-Version: 2.1
Name: ultiplayground
Version: 0.1.5
Summary: My Personal Playground
Home-page: https://github.com/UltiRequiem/python
License: MIT
Keywords: ultirequiem,utilities,playground
Author: Eliaz Bobadilla
Author-email: eliaz.bobadilladev@gmail.com
Requires-Python: >=3.7,<4.0
Classifier: License :: OSI Approved :: MIT License
Classifier: Programming Language :: Python :: 3
Classifier: Programming Language :: Python :: 3.7
Classifier: Programming Language :: Python :: 3.8
Classifier: Programming Language :: Python :: 3.9
Requires-Dist: requests (>=2.26.0,<3.0.0)
Project-URL: Repository, https://github.com/UltiRequiem/python
